[{"vers":"10:1","text":"A MINHA alma tem tédio de minha vida; darei livre curso à minha queixa, falarei na amargura da minha alma."},{"vers":"10:2","text":"Direi a Deus: não me condenes; faze-me saber por que contendes comigo."},{"vers":"10:3","text":"Parece-te bem que me oprimas, que rejeites o trabalho das tuas mãos e resplandeças sobre o conselho dos ímpios?"},{"vers":"10:4","text":"Tens tu porventura olhos de carne? Vês tu como vê o homem?"},{"vers":"10:5","text":"São os teus dias como os dias do homem? Ou são os teus anos como os anos de um homem."},{"vers":"10:6","text":"Para te informares da minha iniquidade, e averiguares o meu pecado?"},{"vers":"10:7","text":"Bem sabes tu que eu não sou ímpio; todavia ninguém há que me livre da tua mão."},{"vers":"10:8","text":"As tuas mãos me fizeram e me entreteceram; e, todavia, me consomes."},{"vers":"10:9","text":"Peço-te que te lembres de que como barro me formaste, e de que ao pó me farás tornar."},{"vers":"10:10","text":"Porventura não me vazaste como leite, e como queijo me não coalhaste?"},{"vers":"10:11","text":"De pele e carne me vestiste e de ossos e nervos me entreteceste."},{"vers":"10:12","text":"Vida e beneficência me concedeste; e o teu cuidado guardou o meu espírito."},{"vers":"10:13","text":"Mas estas cousas as ocultaste no teu coração; bem sei eu que isto esteve contigo."},{"vers":"10:14","text":"Se eu pecar, tu me observas; e da minha iniquidade não me escusarás."},{"vers":"10:15","text":"Se for ímpio, ai de mim! e se for justo, não levantarei a minha cabeça; cheio estou de ignomínia, e olho para a minha miséria."},{"vers":"10:16","text":"Porque se me exalto, tu me caças como a um leão feroz, e de novo fazes maravilhas contra mim."},{"vers":"10:17","text":"Tu renovas contra mim as tuas testemunhas, e multiplicas contra mim a tua ira; reveses e combate estão comigo."},{"vers":"10:18","text":"Por que pois me tiraste da madre? Ah! se então dera o espírito, e olhos nenhuns me vissem!"},{"vers":"10:19","text":"Então fora como se nunca houvera sido: e desde o ventre seria levado à sepultura!"},{"vers":"10:20","text":"Porventura não são poucos os meus dias? Cessa pois, e deixa-me para que por um pouco eu tome alento;"},{"vers":"10:21","text":"Antes que me vá, para nunca mais voltar, à terra da escuridão e da sombra da morte;"},{"vers":"10:22","text":"Terra escuríssima, como a mesma escuridão, terra da sombra da morte e sem ordem alguma, e onde a luz é como a escuridão."},{"vers":"","text":""}]